{
  "cidade": "Fafe",
  "nodes": {
    "Praça Mártires de Ferreira do Amaral": {
      "x": 187.43,
      "y": 162.41
    },
    "Hospital da Misericórdia": {
      "x": 196.15,
      "y": 182.62
    },
    "Parque da Cidade": {
      "x": 231.93,
      "y": 231.93
    },
    "Pavilhão Multiusos": {
      "x": 188.07,
      "y": 202.0
    },
    "Terminal Rodoviário": {
      "x": 165.02,
      "y": 190.45
    },
    "Bebedouro Parque da Cidade": {
      "x": 197.65,
      "y": 245.27
    },
    "Parque Infantil do Centro": {
      "x": 224.13,
      "y": 299.4
    },
    "Ecoponto Multiusos": {
      "x": 181.36,
      "y": 261.21
    }
  },
  "edges": [
    {
      "destino": "Hospital da Misericórdia",
      "acessibilidade": {
        "pavimento": 15,
        "inclinacao": 15,
        "passadeiras": 4,
        "passeios": 15,
        "textura_cego": true,
        "escadas": true
      },
      "ambiente": {
        "temperatura": 20,
        "qualidade_ar": 65,
        "poluicao_sonora": 15,
        "poluicao_visual": 15,
        "nivel_polen": 30,
        "iluminacao": 20,
        "sombra": 15
      },
      "populacao": {
        "transito": false,
        "multidao": true
      },
      "origem_coord": {
        "x": 187.43,
        "y": 162.41
      },
      "destino_coord": {
        "x": 196.15,
        "y": 182.62
      }
    },
    {
      "destino": "Pavilhão Multiusos",
      "acessibilidade": {
        "pavimento": 60,
        "inclinacao": 60,
        "passadeiras": 1,
        "passeios": 80,
        "textura_cego": true,
        "escadas": true
      },
      "ambiente": {
        "temperatura": 27,
        "qualidade_ar": 90,
        "poluicao_sonora": 85,
        "poluicao_visual": 15,
        "nivel_polen": 55,
        "iluminacao": 80,
        "sombra": 80
      },
      "populacao": {
        "transito": false,
        "multidao": false
      },
      "origem_coord": {
        "x": 187.43,
        "y": 162.41
      },
      "destino_coord": {
        "x": 188.07,
        "y": 202.0
      }
    },
    {
      "destino": "Parque da Cidade",
      "acessibilidade": {
        "pavimento": 15,
        "inclinacao": 40,
        "passadeiras": 1,
        "passeios": 80,
        "textura_cego": false,
        "escadas": true
      },
      "ambiente": {
        "temperatura": 35,
        "qualidade_ar": 90,
        "poluicao_sonora": 50,
        "poluicao_visual": 85,
        "nivel_polen": 85,
        "iluminacao": 80,
        "sombra": 45
      },
      "populacao": {
        "transito": true,
        "multidao": false
      },
      "origem_coord": {
        "x": 196.15,
        "y": 182.62
      },
      "destino_coord": {
        "x": 231.93,
        "y": 231.93
      }
    },
    {
      "destino": "Praça Mártires de Ferreira do Amaral",
      "acessibilidade": {
        "pavimento": 85,
        "inclinacao": 15,
        "passadeiras": 4,
        "passeios": 45,
        "textura_cego": false,
        "escadas": true
      },
      "ambiente": {
        "temperatura": 27,
        "qualidade_ar": 65,
        "poluicao_sonora": 85,
        "poluicao_visual": 85,
        "nivel_polen": 55,
        "iluminacao": 80,
        "sombra": 80
      },
      "populacao": {
        "transito": false,
        "multidao": false
      },
      "origem_coord": {
        "x": 196.15,
        "y": 182.62
      },
      "destino_coord": {
        "x": 187.43,
        "y": 162.41
      }
    },
    {
      "destino": "Pavilhão Multiusos",
      "acessibilidade": {
        "pavimento": 60,
        "inclinacao": 60,
        "passadeiras": 1,
        "passeios": 15,
        "textura_cego": false,
        "escadas": false
      },
      "ambiente": {
        "temperatura": 20,
        "qualidade_ar": 10,
        "poluicao_sonora": 85,
        "poluicao_visual": 85,
        "nivel_polen": 85,
        "iluminacao": 45,
        "sombra": 15
      },
      "populacao": {
        "transito": false,
        "multidao": false
      },
      "origem_coord": {
        "x": 231.93,
        "y": 231.93
      },
      "destino_coord": {
        "x": 188.07,
        "y": 202.0
      }
    },
    {
      "destino": "Terminal Rodoviário",
      "acessibilidade": {
        "pavimento": 40,
        "inclinacao": 60,
        "passadeiras": 4,
        "passeios": 45,
        "textura_cego": false,
        "escadas": false
      },
      "ambiente": {
        "temperatura": 35,
        "qualidade_ar": 90,
        "poluicao_sonora": 85,
        "poluicao_visual": 15,
        "nivel_polen": 10,
        "iluminacao": 20,
        "sombra": 80
      },
      "populacao": {
        "transito": false,
        "multidao": false
      },
      "origem_coord": {
        "x": 188.07,
        "y": 202.0
      },
      "destino_coord": {
        "x": 165.02,
        "y": 190.45
      }
    },
    {
      "destino": "Bebedouro Parque da Cidade",
      "acessibilidade": {
        "pavimento": 85,
        "inclinacao": 85,
        "passadeiras": 1,
        "passeios": 15,
        "textura_cego": false,
        "escadas": true
      },
      "ambiente": {
        "temperatura": 27,
        "qualidade_ar": 65,
        "poluicao_sonora": 50,
        "poluicao_visual": 85,
        "nivel_polen": 55,
        "iluminacao": 45,
        "sombra": 80
      },
      "populacao": {
        "transito": false,
        "multidao": false
      },
      "origem_coord": {
        "x": 165.02,
        "y": 190.45
      },
      "destino_coord": {
        "x": 197.65,
        "y": 245.27
      }
    },
    {
      "destino": "Bebedouro Parque da Cidade",
      "acessibilidade": {
        "pavimento": 85,
        "inclinacao": 60,
        "passadeiras": 4,
        "passeios": 45,
        "textura_cego": true,
        "escadas": true
      },
      "ambiente": {
        "temperatura": 35,
        "qualidade_ar": 65,
        "poluicao_sonora": 50,
        "poluicao_visual": 15,
        "nivel_polen": 30,
        "iluminacao": 20,
        "sombra": 15
      },
      "populacao": {
        "transito": false,
        "multidao": false
      },
      "origem_coord": {
        "x": 165.02,
        "y": 190.45
      },
      "destino_coord": {
        "x": 197.65,
        "y": 245.27
      }
    },
    {
      "destino": "Parque Infantil do Centro",
      "acessibilidade": {
        "pavimento": 60,
        "inclinacao": 15,
        "passadeiras": 1,
        "passeios": 45,
        "textura_cego": true,
        "escadas": false
      },
      "ambiente": {
        "temperatura": 20,
        "qualidade_ar": 35,
        "poluicao_sonora": 15,
        "poluicao_visual": 85,
        "nivel_polen": 30,
        "iluminacao": 45,
        "sombra": 15
      },
      "populacao": {
        "transito": true,
        "multidao": false
      },
      "origem_coord": {
        "x": 197.65,
        "y": 245.27
      },
      "destino_coord": {
        "x": 224.13,
        "y": 299.4
      }
    },
    {
      "destino": "Parque da Cidade",
      "acessibilidade": {
        "pavimento": 85,
        "inclinacao": 15,
        "passadeiras": 1,
        "passeios": 80,
        "textura_cego": false,
        "escadas": false
      },
      "ambiente": {
        "temperatura": 27,
        "qualidade_ar": 10,
        "poluicao_sonora": 50,
        "poluicao_visual": 15,
        "nivel_polen": 10,
        "iluminacao": 45,
        "sombra": 45
      },
      "populacao": {
        "transito": true,
        "multidao": true
      },
      "origem_coord": {
        "x": 197.65,
        "y": 245.27
      },
      "destino_coord": {
        "x": 231.93,
        "y": 231.93
      }
    },
    {
      "destino": "Ecoponto Multiusos",
      "acessibilidade": {
        "pavimento": 85,
        "inclinacao": 15,
        "passadeiras": 8,
        "passeios": 80,
        "textura_cego": true,
        "escadas": true
      },
      "ambiente": {
        "temperatura": 20,
        "qualidade_ar": 35,
        "poluicao_sonora": 15,
        "poluicao_visual": 15,
        "nivel_polen": 10,
        "iluminacao": 80,
        "sombra": 45
      },
      "populacao": {
        "transito": true,
        "multidao": false
      },
      "origem_coord": {
        "x": 224.13,
        "y": 299.4
      },
      "destino_coord": {
        "x": 181.36,
        "y": 261.21
      }
    },
    {
      "destino": "Ecoponto Multiusos",
      "acessibilidade": {
        "pavimento": 60,
        "inclinacao": 85,
        "passadeiras": 4,
        "passeios": 80,
        "textura_cego": true,
        "escadas": true
      },
      "ambiente": {
        "temperatura": 20,
        "qualidade_ar": 65,
        "poluicao_sonora": 50,
        "poluicao_visual": 85,
        "nivel_polen": 10,
        "iluminacao": 20,
        "sombra": 15
      },
      "populacao": {
        "transito": true,
        "multidao": true
      },
      "origem_coord": {
        "x": 224.13,
        "y": 299.4
      },
      "destino_coord": {
        "x": 181.36,
        "y": 261.21
      }
    },
    {
      "destino": "Praça Mártires de Ferreira do Amaral",
      "acessibilidade": {
        "pavimento": 15,
        "inclinacao": 85,
        "passadeiras": 4,
        "passeios": 80,
        "textura_cego": false,
        "escadas": false
      },
      "ambiente": {
        "temperatura": 20,
        "qualidade_ar": 65,
        "poluicao_sonora": 50,
        "poluicao_visual": 85,
        "nivel_polen": 55,
        "iluminacao": 80,
        "sombra": 45
      },
      "populacao": {
        "transito": true,
        "multidao": true
      },
      "origem_coord": {
        "x": 181.36,
        "y": 261.21
      },
      "destino_coord": {
        "x": 187.43,
        "y": 162.41
      }
    },
    {
      "destino": "Terminal Rodoviário",
      "acessibilidade": {
        "pavimento": 40,
        "inclinacao": 85,
        "passadeiras": 1,
        "passeios": 80,
        "textura_cego": true,
        "escadas": true
      },
      "ambiente": {
        "temperatura": 27,
        "qualidade_ar": 65,
        "poluicao_sonora": 15,
        "poluicao_visual": 15,
        "nivel_polen": 30,
        "iluminacao": 45,
        "sombra": 80
      },
      "populacao": {
        "transito": false,
        "multidao": false
      },
      "origem_coord": {
        "x": 181.36,
        "y": 261.21
      },
      "destino_coord": {
        "x": 165.02,
        "y": 190.45
      }
    }
  ]
}